maswGui.py
surfwaver.py
threads.py
modswpro/cmpccworkflows.py
modswpro/modarray1D.py
modswpro/modmasw.py
modswpro/modsensor1C.py
modswpro/modwavefieldtransforms.py
res/aquGeomPlot.py
res/gather_plot.py
res/mkcmp.py
res/mkcmpcc.py
surfwaver-0.0.1.dist-info/LICENSE
surfwaver-0.0.1.dist-info/METADATA
surfwaver-0.0.1.dist-info/WHEEL
surfwaver-0.0.1.dist-info/top_level.txt
surfwaver-0.0.1.dist-info/RECORD
