Metadata-Version: 2.1
Name: surfwaver
Version: 0.0.1
Summary: SurfWaveR
Author: Shanu Biswas
Author-email: shanubiswas119@gmail.com
Keywords: MASW,Multichannel Analysis of Surface Waves,Dispersion,Inversion,seismic,active and passive surface wave,SurfWaveR
Classifier: Development Status :: 2 - Pre-Alpha
Classifier: Intended Audience :: Education
Classifier: Intended Audience :: Science/Research
Classifier: Programming Language :: Python :: 3
Classifier: Operating System :: OS Independent
Requires-Python: >=3.6.0
License-File: LICENSE
Requires-Dist: obspy
Requires-Dist: PyQt5
Requires-Dist: swprocess
Requires-Dist: numpy
Requires-Dist: scipy
Requires-Dist: matplotlib
